Metadata-Version: 1.1
Name: pygfolder
Version: 0.0.4
Summary: PyGFolder is a package for managing Google Drive folders as a dictionary.
Home-page: http://github.com/ipazc/pygfolder
Author: Iván de Paz Centeno
Author-email: ipazc@unileon.es
License: MIT
Keywords: pygfolder dict folder file filesystem google drive
Platform: UNKNOWN
Classifier: Environment :: Console
Classifier: Intended Audience :: Developers
Classifier: Intended Audience :: Education
Classifier: Intended Audience :: Science/Research
Classifier: Natural Language :: English
Classifier: Programming Language :: Python :: 3.4
Classifier: Programming Language :: Python :: 3.5
Classifier: Programming Language :: Python :: 3.6
Classifier: Programming Language :: Python :: 3.7
